{
  "currentStep": "publish github pages",
  "heartbeatAt": "2026-07-01T02:55:54.014622+00:00",
  "lockFile": "/Users/skyhong/Documents/Harmonica-in-Taiwan/state/run_pipeline.lock",
  "maxPostAgeDays": 30,
  "message": "",
  "pid": 94605,
  "startedAt": "2026-07-01T02:53:06.704379+00:00",
  "status": "running",
  "steps": [
    {
      "command": [
        "/Library/Developer/CommandLineTools/usr/bin/python3",
        "scripts/build_social_sources.py"
      ],
      "finishedAt": "2026-07-01T02:53:06.770961+00:00",
      "name": "build social sources",
      "returnCode": 0,
      "startedAt": "2026-07-01T02:53:06.705603+00:00",
      "status": "ok"
    },
    {
      "command": [
        "/Library/Developer/CommandLineTools/usr/bin/python3",
        "scripts/youtube_ytdlp_fetcher.py",
        "--max-post-age-days",
        "30"
      ],
      "finishedAt": "2026-07-01T02:53:16.711784+00:00",
      "name": "fetch youtube",
      "returnCode": 0,
      "startedAt": "2026-07-01T02:53:06.771445+00:00",
      "status": "ok"
    },
    {
      "command": [
        "/Library/Developer/CommandLineTools/usr/bin/python3",
        "scripts/apify_facebook_fetcher.py",
        "--days-back",
        "30",
        "--local-max-post-age-days",
        "30",
        "--run"
      ],
      "finishedAt": "2026-07-01T02:53:17.730605+00:00",
      "name": "fetch facebook apify",
      "returnCode": 0,
      "startedAt": "2026-07-01T02:53:16.712415+00:00",
      "status": "ok"
    },
    {
      "command": [
        "/Library/Developer/CommandLineTools/usr/bin/python3",
        "scripts/social_feed_watchdog.py",
        "--max-post-age-days",
        "30"
      ],
      "finishedAt": "2026-07-01T02:55:41.300643+00:00",
      "name": "watch social feeds",
      "returnCode": 0,
      "startedAt": "2026-07-01T02:53:17.733098+00:00",
      "status": "ok"
    },
    {
      "command": [
        "/Library/Developer/CommandLineTools/usr/bin/python3",
        "scripts/build_public_data.py"
      ],
      "finishedAt": "2026-07-01T02:55:42.748390+00:00",
      "name": "build public data",
      "returnCode": 0,
      "startedAt": "2026-07-01T02:55:41.302525+00:00",
      "status": "ok"
    },
    {
      "command": [
        "/Library/Developer/CommandLineTools/usr/bin/python3",
        "scripts/backfill_public_source_pages.py",
        "--skip-fetch"
      ],
      "finishedAt": "2026-07-01T02:55:44.750538+00:00",
      "name": "backfill source pages",
      "returnCode": 0,
      "startedAt": "2026-07-01T02:55:42.748874+00:00",
      "status": "ok"
    },
    {
      "command": [
        "/Library/Developer/CommandLineTools/usr/bin/python3",
        "scripts/build_public_data.py"
      ],
      "finishedAt": "2026-07-01T02:55:46.207889+00:00",
      "name": "rebuild public data",
      "returnCode": 0,
      "startedAt": "2026-07-01T02:55:44.751459+00:00",
      "status": "ok"
    },
    {
      "command": [
        "/Library/Developer/CommandLineTools/usr/bin/python3",
        "scripts/generate_rss_feeds.py"
      ],
      "finishedAt": "2026-07-01T02:55:50.505691+00:00",
      "name": "generate rss feeds",
      "returnCode": 0,
      "startedAt": "2026-07-01T02:55:46.208486+00:00",
      "status": "ok"
    },
    {
      "command": [
        "/Library/Developer/CommandLineTools/usr/bin/python3",
        "scripts/build_status_page.py"
      ],
      "finishedAt": "2026-07-01T02:55:51.766070+00:00",
      "name": "build status page",
      "returnCode": 0,
      "startedAt": "2026-07-01T02:55:50.506674+00:00",
      "status": "ok"
    },
    {
      "command": [
        "/Library/Developer/CommandLineTools/usr/bin/python3",
        "scripts/check_source_coverage.py"
      ],
      "finishedAt": "2026-07-01T02:55:53.411600+00:00",
      "name": "check source coverage",
      "returnCode": 0,
      "startedAt": "2026-07-01T02:55:51.768942+00:00",
      "status": "ok"
    },
    {
      "command": [
        "/Library/Developer/CommandLineTools/usr/bin/python3",
        "scripts/validate_public_outputs.py"
      ],
      "finishedAt": "2026-07-01T02:55:54.013264+00:00",
      "name": "validate public outputs",
      "returnCode": 0,
      "startedAt": "2026-07-01T02:55:53.412641+00:00",
      "status": "ok"
    },
    {
      "command": [
        "/Library/Developer/CommandLineTools/usr/bin/python3",
        "scripts/publish_github_pages.py"
      ],
      "finishedAt": "",
      "name": "publish github pages",
      "returnCode": null,
      "startedAt": "2026-07-01T02:55:54.014608+00:00",
      "status": "running"
    }
  ],
  "version": 1
}
